cosmology/__init__.py
cosmology/a_to_z.py
cosmology/constants.py
cosmology/cosmology.py
data_io/__init__.py
data_io/merge_sims.py
data_io/plots.py
data_io/read_data.py
inference/__init__.py
inference/loglike.py
inference/mcmc.py
model/__init__.py
model/core_functions.py
model/core_functions_pycamb.py
model/integrate_xi.py
model/stable_clustering.py
model/stable_clustering_exec.py
model/v12_lin_approximations.py
model/v12_num_deriv_of_xi.py
model/v12_simulation_driven.py
pairs_toolkit-0.0.1.dist-info/licenses/LICENSE
pairs_toolkit-0.0.1.dist-info/METADATA
pairs_toolkit-0.0.1.dist-info/WHEEL
pairs_toolkit-0.0.1.dist-info/top_level.txt
pairs_toolkit-0.0.1.dist-info/RECORD
