Metadata-Version: 2.4
Name: pairs-toolkit
Version: 0.0.1
Summary: A modular Python toolkit to model, analyze, and compare pairwise velocities and dispersions.
Author: Jorge Farieta
Author-email: Mariana Jaber <jaber@cft.edu.pl>, Antonela Taverna <taverna@cft.edu.pl>
License: MIT License
Requires-Python: >=3.10
License-File: LICENSE
Requires-Dist: numpy
Requires-Dist: scipy>=1.4
Requires-Dist: mpi4py>=3.0.0
Dynamic: license-file
